ds_utils/__init__.py
ds_utils/_modidx.py
ds_utils/ml.py
python_ds_utils-0.0.1.dist-info/LICENSE
python_ds_utils-0.0.1.dist-info/METADATA
python_ds_utils-0.0.1.dist-info/WHEEL
python_ds_utils-0.0.1.dist-info/entry_points.txt
python_ds_utils-0.0.1.dist-info/top_level.txt
python_ds_utils-0.0.1.dist-info/RECORD
